pyplis/__init__.py
pyplis/_init_utils.py
pyplis/_version.py
pyplis/base_img_list.py
pyplis/calib_base.py
pyplis/camera_base_info.py
pyplis/cellcalib.py
pyplis/custom_image_import.py
pyplis/dataset.py
pyplis/dilutioncorr.py
pyplis/doascalib.py
pyplis/exceptions.py
pyplis/fluxcalc.py
pyplis/forms.py
pyplis/geometry.py
pyplis/glob.py
pyplis/helpers.py
pyplis/image.py
pyplis/imagelists.py
pyplis/inout.py
pyplis/model_functions.py
pyplis/optimisation.py
pyplis/plumebackground.py
pyplis/plumespeed.py
pyplis/processing.py
pyplis/setupclasses.py
pyplis/utils.py
pyplis/data/README.rst
pyplis/data/_paths.txt
pyplis/data/cam_info.txt
pyplis/data/my_sources.txt
pyplis/data/no_images_dummy.png
pyplis/data/test_201509160708_F01_335.fts
pyplis/data/testdata_minimal/doas_results/f01_so2_std.dat
pyplis/data/testdata_minimal/doas_results/f02_so2_low.dat
pyplis/data/testdata_minimal/images/EC2_1106307_1R02_2015091606454457_F01_Etna.fts
pyplis/data/testdata_minimal/images/EC2_1106307_1R02_2015091606454717_F02_Etna.fts
pyplis/data/testdata_minimal/images/EC2_1106307_1R02_2015091606593268_D0L_Etna.fts
pyplis/data/testdata_minimal/images/EC2_1106307_1R02_2015091606593410_D1L_Etna.fts
pyplis/data/testdata_minimal/images/EC2_1106307_1R02_2015091606593561_D0H_Etna.fts
pyplis/data/testdata_minimal/images/EC2_1106307_1R02_2015091606593704_D1H_Etna.fts
pyplis/data/testdata_minimal/images/EC2_1106307_1R02_2015091607000301_F01_Etna.fts
pyplis/data/testdata_minimal/images/EC2_1106307_1R02_2015091607000468_F02_Etna.fts
pyplis/data/testdata_minimal/images/EC2_1106307_1R02_2015091607000845_F01_Etna.fts
pyplis/data/testdata_minimal/images/EC2_1106307_1R02_2015091607001021_F02_Etna.fts
pyplis/data/testdata_minimal/images/EC2_1106307_1R02_2015091607001390_F01_Etna.fts
pyplis/data/testdata_minimal/images/EC2_1106307_1R02_2015091607001574_F02_Etna.fts
pyplis/data/testdata_minimal/images/EC2_1106307_1R02_2015091607001943_F01_Etna.fts
pyplis-1.5.0.dist-info/licenses/LICENSE
pyplis-1.5.0.dist-info/METADATA
pyplis-1.5.0.dist-info/WHEEL
pyplis-1.5.0.dist-info/top_level.txt
pyplis-1.5.0.dist-info/RECORD
