Metadata-Version: 2.4
Name: pyplis
Version: 1.5.0
Summary: Python library for the analysis UV SO2 camera data
Author-email: Jonas Gliss <jonasgliss@gmail.com>
Project-URL: Homepage, https://github.com/jgliss/pyplis
Project-URL: Documentation, https://pyplis.readthedocs.io/en/latest/
Classifier: Development Status :: 5 - Production/Stable
Classifier: Intended Audience :: Science/Research
Classifier: Intended Audience :: Education
Classifier: Programming Language :: Python :: 3.9
Classifier: Programming Language :: Python :: 3.10
Classifier: Programming Language :: Python :: 3.11
Classifier: Programming Language :: Python :: 3.12
Requires-Python: >=3.9
License-File: LICENSE
Requires-Dist: numpy
Requires-Dist: scipy
Requires-Dist: pandas
Requires-Dist: astropy
Requires-Dist: matplotlib
Requires-Dist: opencv-python
Requires-Dist: geonum>=1.6
Requires-Dist: pydoas>=2.1
Requires-Dist: progressbar
Requires-Dist: pyproj
Requires-Dist: setuptools_scm
Provides-Extra: dev
Requires-Dist: pytest; extra == "dev"
Requires-Dist: pytest-cov; extra == "dev"
Requires-Dist: sphinx; extra == "dev"
Requires-Dist: sphinx-rtd-theme; extra == "dev"
Dynamic: license-file
